dustpylib-0.7.0.dist-info/METADATA
dustpylib-0.7.0.dist-info/WHEEL
dustpylib-0.7.0.dist-info/LICENSE
dustpylib/__init__.py
dustpylib/dynamics/__init__.py
dustpylib/dynamics/backreaction/__init__.py
dustpylib/dynamics/backreaction/functions_backreaction.py
dustpylib/dynamics/backreaction/setup_backreaction.py
dustpylib/grid/__init__.py
dustpylib/grid/refinement/__init__.py
dustpylib/grid/refinement/refinement.py
dustpylib/planetesimals/__init__.py
dustpylib/planetesimals/formation/__init__.py
dustpylib/planetesimals/formation/formation.py
dustpylib/radtrans/__init__.py
dustpylib/radtrans/radmc3d/__init__.py
dustpylib/radtrans/radmc3d/radmc3d.py
dustpylib/radtrans/slab/__init__.py
dustpylib/radtrans/slab/slab.py
dustpylib/substructures/__init__.py
dustpylib/substructures/gaps/__init__.py
dustpylib/substructures/gaps/gaps.py
dustpylib-0.7.0.dist-info/RECORD
