Metadata-Version: 2.1
Name: dustpylib
Version: 0.7.0
Summary: Library of DustPy extensions
Keywords: science,physics,mathematics,visualization
Author: Matías Garaté
Author-Email: Sebastian Stammler <sebastian.stammler@gmail.com>, Til Birnstiel <til.birnstiel@lmu.de>
Maintainer-Email: Sebastian Stammler <sebastian.stammler@gmail.com>, Tilman Birnstiel <til.birnstiel@lmu.de>
License: BSD 3-Clause License
Classifier: Development Status :: 4 - Beta
Classifier: Environment :: Console
Classifier: Intended Audience :: Developers
Classifier: Intended Audience :: Science/Research
Classifier: License :: OSI Approved :: BSD License
Classifier: Natural Language :: English
Classifier: Operating System :: OS Independent
Classifier: Programming Language :: Python
Classifier: Programming Language :: Python :: 3 :: Only
Classifier: Topic :: Education
Classifier: Topic :: Scientific/Engineering
Classifier: Topic :: Scientific/Engineering :: Astronomy
Classifier: Topic :: Scientific/Engineering :: Physics
Classifier: Topic :: Scientific/Engineering :: Visualization
Project-URL: Repository, https://github.com/stammler/dustpylib/
Project-URL: Documentation, https://dustpylib.readthedocs.io/
Requires-Dist: astropy
Requires-Dist: dsharp_opac
Requires-Dist: dustpy
Requires-Dist: matplotlib
Requires-Dist: numpy
Requires-Dist: scipy
Requires-Dist: simframe
